ckanext/__init__.py
ckanext/relationship/__init__.py
ckanext/relationship/config.py
ckanext/relationship/config_declaration.yaml
ckanext/relationship/helpers.py
ckanext/relationship/plugin.py
ckanext/relationship/presets.yaml
ckanext/relationship/utils.py
ckanext/relationship/views.py
ckanext/relationship/assets/webassets.yml
ckanext/relationship/assets/js/relationship-autocomplete.js
ckanext/relationship/logic/__init__.py
ckanext/relationship/logic/action.py
ckanext/relationship/logic/auth.py
ckanext/relationship/logic/schema.py
ckanext/relationship/logic/validators.py
ckanext/relationship/migration/relationship/alembic.ini
ckanext/relationship/migration/relationship/env.py
ckanext/relationship/migration/relationship/script.py.mako
ckanext/relationship/migration/relationship/versions/520e6ea9f57c_create_relationship_table.py
ckanext/relationship/model/__init__.py
ckanext/relationship/model/base.py
ckanext/relationship/model/relationship.py
ckanext/relationship/templates/page.html
ckanext/relationship/templates/relationship/snippets/asset.html
ckanext/relationship/templates/scheming/display_snippets/related_entity.html
ckanext/relationship/templates/scheming/form_snippets/related_entity.html
ckanext/relationship/templates/scheming/form_snippets/related_entity_with_autocomplete.html
ckanext/relationship/tests/__init__.py
ckanext/relationship/tests/conftest.py
ckanext/relationship/tests/package_with_relationship.yaml
ckanext/relationship/tests/test_plugin.py
ckanext/relationship/tests/test_utils.py
ckanext/relationship/tests/logic/__init__.py
ckanext/relationship/tests/logic/test_action.py
ckanext_relationship-0.2.10.dist-info/LICENSE
ckanext_relationship-0.2.10.dist-info/METADATA
ckanext_relationship-0.2.10.dist-info/WHEEL
ckanext_relationship-0.2.10.dist-info/entry_points.txt
ckanext_relationship-0.2.10.dist-info/top_level.txt
ckanext_relationship-0.2.10.dist-info/RECORD
